MANIFEST.in
README.txt
setup.py
src/dingo/__init__.py
src/dingo/decorators.py
src/dingo/modeladmin.py
src/dingo/registry.py
src/dingo/site.py
src/dingo.egg-info/PKG-INFO
src/dingo.egg-info/SOURCES.txt
src/dingo.egg-info/dependency_links.txt
src/dingo.egg-info/requires.txt
src/dingo.egg-info/top_level.txt
src/dingo.egg-info/zip-safe
src/dingo/templates/admin/change_form.html
src/dingo/templates/admin/change_list.html
src/dingo/templates/admin/extra_actions.html