Metadata-Version: 1.0
Name: dingo
Version: 0.2
Summary: UNKNOWN
Home-page: http://gitorious.org/dingo
Author: Nathan R. Yergler
Author-email: nathan@yergler.net
License: UNKNOWN
Platform: UNKNOWN
Classifier: Development Status :: 3 - Alpha
Classifier: Framework :: Django
Classifier: License :: OSI Approved :: BSD License
